tests/__init__.py
tests/test.py
MethnaniSahbi-0.1.2.dist-info/LICENSE.md
MethnaniSahbi-0.1.2.dist-info/METADATA
MethnaniSahbi-0.1.2.dist-info/WHEEL
MethnaniSahbi-0.1.2.dist-info/top_level.txt
MethnaniSahbi-0.1.2.dist-info/RECORD
