Metadata-Version: 2.1
Name: MethnaniSahbi
Version: 0.1.2
Summary: Une bibliothèque pour la gestion des employés avec une interface graphique en PyQt5 et SQLite
Home-page: https://github.com/Sahbimethnani/MethnaniSahbi
Author: Sahbi Methnani
Author-email: sahbimethnani3@gmail.com
Classifier: Development Status :: 3 - Alpha
Classifier: Intended Audience :: Developers
Classifier: License :: OSI Approved :: MIT License
Classifier: Programming Language :: Python :: 3
Classifier: Programming Language :: Python :: 3.8
Classifier: Programming Language :: Python :: 3.9
Classifier: Programming Language :: Python :: 3.10
Classifier: Programming Language :: Python :: 3.11
Classifier: Programming Language :: Python :: 3.12
Classifier: Operating System :: OS Independent
Requires-Python: >=3.6
License-File: LICENSE.md
Requires-Dist: PyQt5
Requires-Dist: pandas
Requires-Dist: openpyxl
